pg_engine/__init__.py
pg_engine/column.py
pg_engine/database.py
pg_engine/errors.py
pg_engine/events.py
pg_engine/model.py
pg_engine/relation.py
sirtimid_orm-0.2.dist-info/METADATA
sirtimid_orm-0.2.dist-info/WHEEL
sirtimid_orm-0.2.dist-info/top_level.txt
sirtimid_orm-0.2.dist-info/RECORD
