Metadata-Version: 2.1
Name: sirtimid-orm
Version: 0.2
Requires-Dist: psycopg2
